netops_cadiz/__init__.py
netops_cadiz/netops.py
netops_cadiz-0.1.0.dist-info/LICENSE.txt
netops_cadiz-0.1.0.dist-info/METADATA
netops_cadiz-0.1.0.dist-info/WHEEL
netops_cadiz-0.1.0.dist-info/top_level.txt
netops_cadiz-0.1.0.dist-info/RECORD
