Metadata-Version: 2.1
Name: netops_cadiz
Version: 0.1.0
Summary: Python package to retrieve spectral values for satellite bands from field Spectroradiometers data
Home-page: https://github.com/Digdgeo/Netops_Cadiz
Author: Diego Garcia Diaz, Maria Dolores Raya-Sereno
Author-email: digd.geografo@gmail.com, mdolores.raya@cchs.csic.es
License: MIT
Requires-Python: >=3.8
License-File: LICENSE.txt
Requires-Dist: numpy
Requires-Dist: pandas
Requires-Dist: matplotlib
Requires-Dist: scipy
Requires-Dist: specdal >=0.2.1
Requires-Dist: openpyxl >=3.1.4
